README.rst
setup.py
fabfile/__init__.py
fabfile/templates.py
openbudgets/__init__.py
openbudgets/dashboard.py
openbudgets/urls.py
openbudgets/wsgi.py
openbudgets.egg-info/PKG-INFO
openbudgets.egg-info/SOURCES.txt
openbudgets.egg-info/dependency_links.txt
openbudgets.egg-info/not-zip-safe
openbudgets.egg-info/requires.txt
openbudgets.egg-info/top_level.txt
openbudgets/api/__init__.py
openbudgets/api/models.py
openbudgets/api/tests.py
openbudgets/api/urls.py
openbudgets/api/views.py
openbudgets/api/v1/__init__.py
openbudgets/api/v1/urls.py
openbudgets/api/v1/views.py
openbudgets/apps/__init__.py
openbudgets/apps/accounts/__init__.py
openbudgets/apps/accounts/admin.py
openbudgets/apps/accounts/factories.py
openbudgets/apps/accounts/forms.py
openbudgets/apps/accounts/models.py
openbudgets/apps/accounts/serializers.py
openbudgets/apps/accounts/tests.py
openbudgets/apps/accounts/migrations/0001_initial.py
openbudgets/apps/accounts/migrations/0002_fixtures.py
openbudgets/apps/accounts/migrations/__init__.py
openbudgets/apps/accounts/urls/__init__.py
openbudgets/apps/accounts/urls/api.py
openbudgets/apps/accounts/urls/ui.py
openbudgets/apps/accounts/views/__init__.py
openbudgets/apps/accounts/views/api.py
openbudgets/apps/accounts/views/ui.py
openbudgets/apps/contexts/__init__.py
openbudgets/apps/contexts/factories.py
openbudgets/apps/contexts/models.py
openbudgets/apps/contexts/serializers.py
openbudgets/apps/contexts/tests.py
openbudgets/apps/contexts/migrations/0001_initial.py
openbudgets/apps/contexts/migrations/__init__.py
openbudgets/apps/contexts/urls/__init__.py
openbudgets/apps/contexts/urls/api.py
openbudgets/apps/contexts/views/__init__.py
openbudgets/apps/contexts/views/api.py
openbudgets/apps/entities/__init__.py
openbudgets/apps/entities/admin.py
openbudgets/apps/entities/factories.py
openbudgets/apps/entities/managers.py
openbudgets/apps/entities/models.py
openbudgets/apps/entities/serializers.py
openbudgets/apps/entities/tests.py
openbudgets/apps/entities/migrations/0001_initial.py
openbudgets/apps/entities/migrations/__init__.py
openbudgets/apps/entities/urls/__init__.py
openbudgets/apps/entities/urls/api.py
openbudgets/apps/entities/urls/ui.py
