Metadata-Version: 1.0
Name: openbudgets
Version: 0.0.1-alpha
Summary: (WIP - DO NOT USE) A web app and web API for storing, accessing, visualizing and comparing budgetary data.
Home-page: https://github.com/openbudgets/openbudgets
Author: Paul Walsh, Yehonatan Daniv
Author-email: paulywalsh@gmail.com, maggotfish@gmail.com
License: BSD
Platform: UNKNOWN
